jinja2yaml-0.1.5.dist-info/METADATA
jinja2yaml-0.1.5.dist-info/WHEEL
jinja2yaml-0.1.5.dist-info/licenses/LICENSE
jinja2yaml/__init__.py
jinja2yaml/yamlloader.py
jinja2yaml-0.1.5.dist-info/RECORD
