Metadata-Version: 2.1
Name: jinja2yaml
Version: 0.1.5
Summary: YamlLoader for jinja2
Keywords: jinja2 jinja2-template jinja2-extention jinja2yaml yaml template
Home-page: https://github.com/vd2org/jinja2yaml
Author-Email: vd <jinja2yaml@vd2.org>
License: Copyright 2017-2024 Vd <jinja2yaml@vd2.org>
Classifier: Development Status :: 4 - Beta
Classifier: Intended Audience :: Developers
Classifier: Intended Audience :: Information Technology
Classifier: Intended Audience :: System Administrators
Classifier: Topic :: Software Development
Classifier: Topic :: Software Development :: Libraries
Classifier: Topic :: Software Development :: Libraries :: Python Modules
Classifier: Topic :: Software Development :: User Interfaces
Classifier: License :: OSI Approved :: MIT License
Classifier: Programming Language :: Python :: 3
Classifier: Programming Language :: Python :: 3.8
Classifier: Programming Language :: Python :: 3.9
Classifier: Programming Language :: Python :: 3.10
Classifier: Programming Language :: Python :: 3.11
Classifier: Programming Language :: Python :: 3.12
Project-URL: Homepage, https://github.com/vd2org/jinja2yaml
Project-URL: Repository, https://github.com/vd2org/jinja2yaml.git
Project-URL: Issues, https://github.com/vd2org/jinja2yaml/issues
Requires-Python: <3.13,>=3.8
Requires-Dist: jinja2~=3.1.3
Requires-Dist: pyyaml~=6.0.1
